cognito_overlay/__init__.py
cognito_overlay/_auth.py
cognito_overlay/_config.py
cognito_overlay/_defaults.py
cognito_overlay/users.py
src/__init__.py
src/_auth.py
src/_config.py
src/_defaults.py
src/users.py
cognito_overlay-0.0.1.dev15.dist-info/METADATA
cognito_overlay-0.0.1.dev15.dist-info/WHEEL
cognito_overlay-0.0.1.dev15.dist-info/top_level.txt
cognito_overlay-0.0.1.dev15.dist-info/RECORD
