Metadata-Version: 2.1
Name: cognito-overlay
Version: 0.0.1.dev15
Summary: Pseudo-application for simplifying authentication with Cognito
Home-page: https://github.com/cadetstar/cognito_overlay
Author: Michael Madison
Author-email: cadetstar@hotmail.com
License: UNKNOWN
Platform: UNKNOWN
Classifier: Programming Language :: Python :: 3
Classifier: License :: OSI Approved :: MIT License
Classifier: Operating System :: OS Independent
Requires-Python: >=3.6
Requires-Dist: boto3 (==1.12.35)
Requires-Dist: Flask (==1.1.2)
